model_card_printer/__init__.py
model_card_printer/core.py
model_card_printer/model_card.py
model_card_printer/model_card_components.py
model_card_printer/utils/__init__.py
model_card_printer/utils/convert_shap_to_plotly.py
model_card_printer/utils/html_utils.py
model_card_printer/utils/model_card_style.css
model_card_printer-0.1.1.dist-info/METADATA
model_card_printer-0.1.1.dist-info/WHEEL
model_card_printer-0.1.1.dist-info/top_level.txt
model_card_printer-0.1.1.dist-info/RECORD
