Metadata-Version: 2.4
Name: model-card-printer
Version: 0.1.1
Summary: A streamlined approach to model card generation for machine learning models
Author-email: Daniel Ng <ngdanieljr@gmail.com>
Maintainer-email: Daniel Ng <ngdanieljr@gmail.com>
License-Expression: Apache-2.0
Project-URL: Repository, https://github.com/backyardmaker/model-card-printer.git
Keywords: model card,card,model,model documentation,ml documentation,ml model,ml model documentation
Classifier: Development Status :: 5 - Production/Stable
Classifier: Intended Audience :: Developers
Classifier: Topic :: Scientific/Engineering :: Artificial Intelligence
Classifier: Programming Language :: Python :: 3.9
Classifier: Programming Language :: Python :: 3.10
Classifier: Programming Language :: Python :: 3.11
Classifier: Programming Language :: Python :: 3.12
Requires-Python: >=3.9
Requires-Dist: beautifulsoup4==4.13.3
Requires-Dist: bs4==0.0.2
Requires-Dist: ipython==8.31.0
Requires-Dist: ipywidgets==8.1.5
Requires-Dist: markdown==3.7
Requires-Dist: numpy==2.1.3
Requires-Dist: pandas==2.2.3
Requires-Dist: plotly==6.0.1
Requires-Dist: pytest==8.3.4
Requires-Dist: pytest-cov==6.0.0
Requires-Dist: shap==0.47.1
Provides-Extra: shap
Requires-Dist: numpy==2.1.3; extra == "shap"
Requires-Dist: pandas==2.2.3; extra == "shap"
Requires-Dist: plotly==6.0.1; extra == "shap"
Requires-Dist: shap==0.47.1; extra == "shap"
